autonaming-0.1.0.dist-info/METADATA
autonaming-0.1.0.dist-info/WHEEL
autonaming-0.1.0.dist-info/entry_points.txt
autonaming-0.1.0.dist-info/licenses/LICENSE
autonaming/__init__.py
autonaming/exps.py
autonaming-0.1.0.dist-info/RECORD
