Metadata-Version: 2.4
Name: autonaming
Version: 0.1.0
Summary: Auto naming for experiments
Author-Email: Honghua Dong <dhh19951@gmail.com>
License-Expression: MIT
Requires-Python: >=3.9
Requires-Dist: applang>=0.1.5
Requires-Dist: rich
